__init__.py
metamathpy/__init__.py
metamathpy/database.py
metamathpy/environment.py
metamathpy/obvious.py
metamathpy/parse.py
metamathpy/proof.py
metamathpy/scratch.py
metamathpy/setmm.py
metamathpy/solitaire.py
metamathpy/theory.py
metamathpy/training_data.py
metamathpy/unification.py
mmmine/__init__.py
mmmine/expansion.py
mmmine/raw.py
mmmine/scratch.py
mmmine/used.py
metamath_py-0.0.7.dist-info/LICENSE
metamath_py-0.0.7.dist-info/METADATA
metamath_py-0.0.7.dist-info/WHEEL
metamath_py-0.0.7.dist-info/top_level.txt
metamath_py-0.0.7.dist-info/RECORD
