Metadata-Version: 2.1
Name: metamath-py
Version: 0.0.7
Summary: A Python interface to Metamath
Author-email: "Garrett E. Katz" <garrett.katz@gmail.com>
Project-URL: Homepage, https://github.com/garrettkatz/mmpy
Project-URL: Bug Tracker, https://github.com/garrettkatz/mmpy/issues
Classifier: Programming Language :: Python :: 3
Classifier: License :: OSI Approved :: MIT License
Classifier: Operating System :: OS Independent
Requires-Python: >=3.7
License-File: LICENSE
